<?xml version="1.0" encoding="utf-8"?>
<!DOCTYPE hibernate-mapping PUBLIC "-//Hibernate/Hibernate Mapping DTD 3.0//EN"
"http://hibernate.sourceforge.net/hibernate-mapping-3.0.dtd">
<!-- 
    Mapping file autogenerated by MyEclipse Persistence Tools
-->
<hibernate-mapping>
    <class name="com.hontek.sys.pojo.TsUser" table="TS_USER">
        <id name="userId">
            <column name="USER_ID"/>
             <generator class="assigned"/>
        </id>
        <property name="entId">
            <column name="ent_id" />
        </property>
        <property name="userName">
            <column name="USER_NAME" length="50" />
        </property>
        <property name="password">
            <column name="PASSWORD" length="40" />
        </property>
        <property name="nickname" >
            <column name="NICKNAME" length="50" />
        </property>
        <property name="sex">
            <column name="SEX" length="2" />
        </property>
        <property name="age" >
            <column name="AGE" length="3" />
        </property>
        <property name="birthDate">
            <column name="BIRTH_DATE" length="20" />
        </property>
        <property name="intrest" >
            <column name="INTREST" length="300" />
        </property>
        <property name="flag">
            <column name="FLAG" length="20" />
        </property>
        <property name="phone">
            <column name="PHONE" length="20" />
        </property>
        <property name="email" >
            <column name="EMAIL" length="30" />
        </property>
        <property name="sts">
            <column name="STS" length="2" />
        </property>
        <property name="crtUserId">
            <column name="CRT_USER_ID" length="10" />
        </property>
        <property name="regDate">
            <column name="REG_DATE" length="20" />
        </property>
        <property name="signature" >
            <column name="SIGNATURE" length="100" />
        </property>
        <property name="qqnum" >
            <column name="QQNUM" length="30" />
        </property>
        <property name="tel">
            <column name="TEL" length="30" />
        </property>
        <property name="fax">
            <column name="FAX" length="30" />
        </property>
        <property name="addr">
            <column name="ADDR" length="100" />
        </property>
        <property name="admin">
            <column name="ADMIN" length="5" />
        </property>
    </class>
</hibernate-mapping>
